Verilog/Lab_1/Ex2_FullAdder/full_adder.v
// Author: Your Name
// File: full_adder.v
// Description: A Full Adder in Verilog
// Module: full_adder
// Inputs: a, b, cin
// Outputs: sum, cout

module full_adder (a, b, cin, sum, cout);

// Define the input and output ports
input a, b, cin;
output sum, cout;

// Define IO wires and registers 
wire a, b, cin;  // INPUTS - defined as wires
wire sum, cout;  // OUTPUTS - defined as wires

// Implement the Full Adder logic
assign sum = a ^ b ^ cin;  // XOR for sum
assign cout = (a & b) | (b & cin) | (a & cin);  // OR for carry out

endmodule

Verilog/Lab_1/Ex2_FullAdder/tb_full_adder.v
// Author: Your Name
// File: tb_full_adder.v
// Description: Testbench for the Full Adder
// Module: tb_full_adder
// Inputs: none
// Outputs: none

module tb_full_adder;     // Testbench for Full Adder

// Internal wires and registers (if any)
reg a, b, cin;            // Registers to store test inputs
wire sum, cout;           // Wires to capture the outputs

// Instantiate the Full Adder
full_adder dut (
    .a(a),
    .b(b),
    .cin(cin),
    .sum(sum),
    .cout(cout)
);

// Test procedure
initial begin
    $dumpfile("full_adder.vcd");         // Specify the name of the VCD file
    $dumpvars(0, tb_full_adder);         // Dump all variables in the testbench

    // Apply test inputs
    a = 0; b = 0; cin = 0; #10;  // Wait 10 time units
    a = 0; b = 0; cin = 1; #10;
    a = 0; b = 1; cin = 0; #10;
    a = 0; b = 1; cin = 1; #10;
    a = 1; b = 0; cin = 0; #10;
    a = 1; b = 0; cin = 1; #10;
    a = 1; b = 1; cin = 0; #10;
    a = 1; b = 1; cin = 1; #10;

    // End simulation
    $finish;
end

endmodule

Verilog/Lab_1/Ex2_FullAdder/full_adder.vcd
$date
	Wed Mar  5 16:03:08 2025
$end
$version
	Icarus Verilog
$end
$timescale
	1s
$end
$scope module tb_full_adder $end
$var wire 1 ! sum $end
$var wire 1 " cout $end
$var reg 1 # a $end
$var reg 1 $ b $end
$var reg 1 % cin $end
$scope module dut $end
$var wire 1 # a $end
$var wire 1 $ b $end
$var wire 1 % cin $end
$var wire 1 " cout $end
$var wire 1 ! sum $end
$upscope $end
$upscope $end
$enddefinitions $end
$comment Show the parameter values. $end
$dumpall
$end
#0
$dumpvars
0%
0$
0#
0"
0!
$end
#10
1!
1%
#20
0%
1$
#30
1"
0!
1%
#40
0"
1!
0%
0$
1#
#50
1"
0!
1%
#60
0%
1$
#70
1!
1%
